LICENSE
MANIFEST.in
README.md
README.rst
pyproject.toml
setup.cfg
setup.py
countries/__init__.py
countries/admin.py
countries/apps.py
countries/models.py
countries/serializers.py
countries/tests.py
countries/urls.py
countries/utils.py
countries/views.py
countries/data/City-entreviable.json
countries/data/Country-ENTERVIALBE.json
countries/data/Nationality.json
countries/data/__init__.py
countries/data/add_flags_to_country.py
countries/data/flags/ad.png
countries/data/flags/ae.png
countries/data/flags/af.png
countries/data/flags/ag.png
countries/data/flags/ai.png
countries/data/flags/al.png
countries/data/flags/am.png
countries/data/flags/ao.png
countries/data/flags/aq.png
countries/data/flags/ar.png
countries/data/flags/as.png
countries/data/flags/at.png
countries/data/flags/au.png
countries/data/flags/aw.png
countries/data/flags/ax.png
countries/data/flags/az.png
countries/data/flags/ba.png
countries/data/flags/bb.png
countries/data/flags/bd.png
countries/data/flags/be.png
countries/data/flags/bf.png
countries/data/flags/bg.png
countries/data/flags/bh.png
countries/data/flags/bi.png
countries/data/flags/bj.png
countries/data/flags/bl.png
countries/data/flags/bm.png
countries/data/flags/bn.png
countries/data/flags/bo.png
countries/data/flags/bq.png
countries/data/flags/br.png
countries/data/flags/bs.png
countries/data/flags/bt.png
countries/data/flags/bv.png
countries/data/flags/bw.png
countries/data/flags/by.png
countries/data/flags/bz.png
countries/data/flags/ca.png
countries/data/flags/cc.png
countries/data/flags/cd.png
countries/data/flags/cf.png
countries/data/flags/cg.png
countries/data/flags/ch.png
countries/data/flags/ci.png
countries/data/flags/ck.png
countries/data/flags/cl.png
countries/data/flags/cm.png
countries/data/flags/cn.png
countries/data/flags/co.png
countries/data/flags/cr.png
countries/data/flags/cu.png
countries/data/flags/cv.png
countries/data/flags/cw.png
countries/data/flags/cx.png
countries/data/flags/cy.png
countries/data/flags/cz.png
logatta_countries.egg-info/PKG-INFO
logatta_countries.egg-info/SOURCES.txt
logatta_countries.egg-info/dependency_links.txt
logatta_countries.egg-info/requires.txt
logatta_countries.egg-info/top_level.txt